HISTORY.md
LICENSE
MANIFEST.in
README.md
requirements.txt
setup.py
pythonipsum/__init__.py
pythonipsum/api.py
pythonipsum.egg-info/PKG-INFO
pythonipsum.egg-info/SOURCES.txt
pythonipsum.egg-info/dependency_links.txt
pythonipsum.egg-info/not-zip-safe
pythonipsum.egg-info/requires.txt
pythonipsum.egg-info/top_level.txt
pythonipsum/data/dictionary.txt
pythonipsum/data/sample.txt
specs/case_get_paragraphs.py
specs/case_get_sentences.py