Metadata-Version: 1.1
Name: pythonipsum
Version: 0.2
Summary: A lorem ipsum generator for the Python world.
Home-page: https://github.com/mpirnat/pythonipsum/
Author: Mike Pirnat
Author-email: mpirnat@gmail.com
License: Copyright (C) 2013, Mike Pirnat <mpirnat@gmail.com>
